Workbook
Name patrimonio: Simulação!$D$22
Name qtd_anos: Simulação!$D$20
Name rend_carteira: Simulação!$D$14
Name salario: Simulação!$D$13
Name sug_inv: Simulação!$D$15
Name taxa_rend: Simulação!$D$21
Name valor_inv: Simulação!$D$19

Sheet Simulação
B12: CONFIGURAÇÕES
B13: Salário | D13: 1600
B14: Rendimento Carteira | D14: 0.01
B15: Sugestão de Investimento (30%) | D15: =salario*0.3 -> 480
B18: INVESTIMENTO MENSAL
B19: Quanto investir por mês ? | D19: 500
B20: Por Quantos Anos ? | D20: 5
B21: Taxa de Rendimento mensal ? | D21: 0.012
B22: Patrimônio acumulado ? | D22: =FV(taxa_rend,qtd_anos*12,valor_inv*-1) -> 43568.636
B23: Dividendos Mensais ? | D23: =patrimonio*rend_carteira -> 435.68636
B26: CENÁRIOS | D26: DIVIDENDOS
A27: 2 | B27: Quanto em 2 Anos ? | C27: =FV(taxa_rend,A27*12,valor_inv*-1) -> 13811.367 | D27: =C27*rend_carteira -> 138.11367
A28: 5 | B28: Quanto em 5 Anos ? | C28: =FV(taxa_rend,A28*12,valor_inv*-1) -> 43568.636 | D28: =C28*rend_carteira -> 435.68636
A29: 10 | B29: Quanto em 10 Anos ? | C29: =FV(taxa_rend,A29*12,valor_inv*-1) -> 132694.7 | D29: =C29*rend_carteira -> 1326.947
A30: 20 | B30: Quanto em 20 Anos ? | C30: =FV(taxa_rend,A30*12,valor_inv*-1) -> 687978.58 | D30: =C30*rend_carteira -> 6879.7858
A31: 30 | B31: Quanto em 30 Anos ? | C31: =FV(taxa_rend,A31*12,valor_inv*-1) -> 3011659.9 | D31: =C31*rend_carteira -> 30116.599
B34: PERFIL | C34: Moderado
B35: Valor a ser investido por mês | C35: 500
B37: TIPO DE FII | C37: Percentual Sugerido | D37: Valores
B38: PAPEL | C38: =VLOOKUP(Simulação!$C$34&"-"&Simulação!$B38,tab_de_apoio!$A:$D,4,FALSE) -> 0.32 | D38: =C38*$C$35 -> 160
B39: TIJOLO | C39: =VLOOKUP(Simulação!$C$34&"-"&Simulação!$B39,tab_de_apoio!$A:$D,4,FALSE) -> 0.35 | D39: =C39*$C$35 -> 175
B40: HÍBRIDOS | C40: =VLOOKUP(Simulação!$C$34&"-"&Simulação!$B40,tab_de_apoio!$A:$D,4,FALSE) -> 0.08 | D40: =C40*$C$35 -> 40
B41: FOFs | C41: =VLOOKUP(Simulação!$C$34&"-"&Simulação!$B41,tab_de_apoio!$A:$D,4,FALSE) -> 0.05 | D41: =C41*$C$35 -> 25
B42: DESENVOLVIMENTO | C42: =VLOOKUP(Simulação!$C$34&"-"&Simulação!$B42,tab_de_apoio!$A:$D,4,FALSE) -> 0.1 | D42: =C42*$C$35 -> 50
B43: HOTELARIAS | C43: =VLOOKUP(Simulação!$C$34&"-"&Simulação!$B43,tab_de_apoio!$A:$D,4,FALSE) -> 0.1 | D43: =C43*$C$35 -> 50
D44: =SUM(D38:D43) -> 500

Sheet tab_de_apoio
A3: CHAVE | B3: PERFIL | C3: TIPO DE FII | D3: %
A4: =B4&"-"&C4 -> Conservador-PAPEL | B4: Conservador | C4: PAPEL | D4: 0.3
A5: =B5&"-"&C5 -> Conservador-TIJOLO | B5: Conservador | C5: TIJOLO | D5: 0.5
A6: =B6&"-"&C6 -> Conservador-HÍBRIDOS | B6: Conservador | C6: HÍBRIDOS | D6: 0.1
A7: =B7&"-"&C7 -> Conservador-FOFs | B7: Conservador | C7: FOFs | D7: 0.1
A8: =B8&"-"&C8 -> Conservador-DESENVOLVIMENTO | B8: Conservador | C8: DESENVOLVIMENTO | D8: 0
A9: =B9&"-"&C9 -> Conservador-HOTELARIAS | B9: Conservador | C9: HOTELARIAS | D9: 0
A10: =B10&"-"&C10 -> Moderado-PAPEL | B10: Moderado | C10: PAPEL | D10: 0.32
A11: =B11&"-"&C11 -> Moderado-TIJOLO | B11: Moderado | C11: TIJOLO | D11: 0.35
A12: =B12&"-"&C12 -> Moderado-HÍBRIDOS | B12: Moderado | C12: HÍBRIDOS | D12: 0.08
A13: =B13&"-"&C13 -> Moderado-FOFs | B13: Moderado | C13: FOFs | D13: 0.05
A14: =B14&"-"&C14 -> Moderado-DESENVOLVIMENTO | B14: Moderado | C14: DESENVOLVIMENTO | D14: 0.1
A15: =B15&"-"&C15 -> Moderado-HOTELARIAS | B15: Moderado | C15: HOTELARIAS | D15: 0.1
... A21: =B21&"-"&C21 -> Agressivo-HOTELARIAS | B21: Agressivo | C21: HOTELARIAS | D21: 0.1
